duet_tools/__init__.py
duet_tools/calibration.py
duet_tools/example.py
duet_tools/inputs.py
duet_tools/landfire.py
duet_tools/utils.py
duet_tools/data/REF_SPECIES.csv
duet_tools/data/sb40_parameters.csv
duet_tools-1.0.1.dist-info/licenses/LICENSE
duet_tools-1.0.1.dist-info/METADATA
duet_tools-1.0.1.dist-info/WHEEL
duet_tools-1.0.1.dist-info/top_level.txt
duet_tools-1.0.1.dist-info/RECORD
