Metadata-Version: 2.4
Name: duet-tools
Version: 1.0.1
Summary: Output management tools for LANL DUET program
Home-page: https://github.com/nmc-cafes/duet-tools
License: MIT
Project-URL: Bug Tracker, https://github.com/nmc-cafes/duet-tools/issues
Classifier: Intended Audience :: Developers
Classifier: Intended Audience :: Science/Research
Classifier: License :: OSI Approved :: MIT License
Classifier: Operating System :: OS Independent
Classifier: Programming Language :: Python :: 3
Classifier: Programming Language :: Python :: 3.10
Classifier: Programming Language :: Python :: 3.11
Classifier: Programming Language :: Python :: 3.12
Classifier: Topic :: Scientific/Engineering
Requires-Python: >=3.10
License-File: LICENSE
Requires-Dist: numpy
Requires-Dist: pandas
Requires-Dist: scipy
Requires-Dist: pyshp
Requires-Dist: geojson
Provides-Extra: landfire
Requires-Dist: pandas; extra == "landfire"
Requires-Dist: geojson; extra == "landfire"
Requires-Dist: shapely; extra == "landfire"
Requires-Dist: pyproj; extra == "landfire"
Requires-Dist: landfire[geospatial]; extra == "landfire"
Requires-Dist: rasterio; extra == "landfire"
Requires-Dist: pyshp; extra == "landfire"
Requires-Dist: geojson; extra == "landfire"
Dynamic: classifier
Dynamic: description
Dynamic: description-content-type
Dynamic: home-page
Dynamic: license
Dynamic: license-file
Dynamic: project-url
Dynamic: provides-extra
Dynamic: requires-dist
Dynamic: requires-python
Dynamic: summary
